codehackscalculator/__init__.py
codehackscalculator_tapas-0.1.dist-info/LICENSE.txt
codehackscalculator_tapas-0.1.dist-info/METADATA
codehackscalculator_tapas-0.1.dist-info/WHEEL
codehackscalculator_tapas-0.1.dist-info/top_level.txt
codehackscalculator_tapas-0.1.dist-info/RECORD
